pyninjotiff/__init__.py
pyninjotiff/ninjotiff.py
pyninjotiff/ninjotiff_config-file_satpy_example.py
pyninjotiff/ninjotiff_example
pyninjotiff/ninjotiff_satpy_example
pyninjotiff/rgb_ninjotiff_satpy_example
pyninjotiff/tifffile.py
pyninjotiff/version.py
pyninjotiff/tests/test_ninjotiff.py
pyninjotiff-0.4.5.dist-info/METADATA
pyninjotiff-0.4.5.dist-info/WHEEL
pyninjotiff-0.4.5.dist-info/licenses/LICENSE
pyninjotiff-0.4.5.dist-info/RECORD
